open_skills/__init__.py
open_skills/config.py
open_skills/main.py
open_skills/api/__init__.py
open_skills/api/deps.py
open_skills/api/router.py
open_skills/api/schemas.py
open_skills/cli/__init__.py
open_skills/cli/main.py
open_skills/core/__init__.py
open_skills/core/artifacts.py
open_skills/core/crypto.py
open_skills/core/exceptions.py
open_skills/core/executor.py
open_skills/core/library.py
open_skills/core/manager.py
open_skills/core/packing.py
open_skills/core/rbac.py
open_skills/core/router.py
open_skills/core/streaming.py
open_skills/core/telemetry.py
open_skills/core/adapters/__init__.py
open_skills/core/adapters/agent_tool_api.py
open_skills/core/adapters/discovery.py
open_skills/core/adapters/prompt_injection.py
open_skills/db/__init__.py
open_skills/db/base.py
open_skills/db/models.py
open_skills/db/migrations/env.py
open_skills/db/migrations/script.py.mako
open_skills/db/migrations/versions/001_initial_schema.py
open_skills/integrations/__init__.py
open_skills/integrations/fastapi_integration.py
open_skills/service/__init__.py
open_skills/service/main.py
open_skills/service/api/__init__.py
open_skills/service/api/deps.py
open_skills/service/api/router.py
open_skills/service/api/schemas.py
open_skills-0.2.0.dist-info/licenses/LICENSE
open_skills-0.2.0.dist-info/METADATA
open_skills-0.2.0.dist-info/WHEEL
open_skills-0.2.0.dist-info/entry_points.txt
open_skills-0.2.0.dist-info/top_level.txt
open_skills-0.2.0.dist-info/RECORD
