Metadata-Version: 2.4
Name: open-skills
Version: 0.2.0
Summary: Framework-agnostic skills subsystem for Python AI agents - embed directly or deploy as a service
Author: Richard Scheiwe
Maintainer: Richard Scheiwe
License: MIT License
Project-URL: Homepage, https://github.com/rscheiwe/open-skills
Project-URL: Documentation, https://github.com/rscheiwe/open-skills#readme
Project-URL: Repository, https://github.com/rscheiwe/open-skills
Project-URL: Bug Tracker, https://github.com/rscheiwe/open-skills/issues
Project-URL: Changelog, https://github.com/rscheiwe/open-skills/blob/main/CHANGELOG.md
Project-URL: Source Code, https://github.com/rscheiwe/open-skills
Keywords: ai,agent,agents,skills,llm,openai,anthropic,langchain,tools,function-calling,fastapi,async,plugin-system,automation,versioning,embeddings
Classifier: Development Status :: 4 - Beta
Classifier: Intended Audience :: Developers
Classifier: License :: OSI Approved :: MIT License
Classifier: Operating System :: OS Independent
Classifier: Programming Language :: Python :: 3
Classifier: Programming Language :: Python :: 3.11
Classifier: Programming Language :: Python :: 3.12
Classifier: Programming Language :: Python :: 3 :: Only
Classifier: Topic :: Software Development :: Libraries :: Python Modules
Classifier: Topic :: Scientific/Engineering :: Artificial Intelligence
Classifier: Framework :: FastAPI
Classifier: Framework :: AsyncIO
Classifier: Typing :: Typed
Requires-Python: >=3.11
License-File: LICENSE
Requires-Dist: fastapi>=0.109.0
Requires-Dist: uvicorn[standard]>=0.27.0
Requires-Dist: pydantic>=2.6.0
Requires-Dist: pydantic-settings>=2.1.0
Requires-Dist: sqlalchemy>=2.0.25
Requires-Dist: asyncpg>=0.29.0
Requires-Dist: alembic>=1.13.0
Requires-Dist: pgvector>=0.2.4
Requires-Dist: httpx>=0.26.0
Requires-Dist: python-multipart>=0.0.6
Requires-Dist: python-jose[cryptography]>=3.3.0
Requires-Dist: passlib[bcrypt]>=1.7.4
Requires-Dist: click>=8.1.7
Requires-Dist: rich>=13.7.0
Requires-Dist: pyyaml>=6.0.1
Requires-Dist: python-dotenv>=1.0.0
Requires-Dist: sse-starlette>=2.0.0
Requires-Dist: structlog>=24.1.0
Provides-Extra: dev
Requires-Dist: pytest>=7.4.0; extra == "dev"
Requires-Dist: pytest-asyncio>=0.23.0; extra == "dev"
Requires-Dist: pytest-cov>=4.1.0; extra == "dev"
Requires-Dist: black>=24.0.0; extra == "dev"
Requires-Dist: ruff>=0.1.0; extra == "dev"
Requires-Dist: mypy>=1.8.0; extra == "dev"
Requires-Dist: httpx>=0.26.0; extra == "dev"
Provides-Extra: langfuse
Requires-Dist: langfuse>=2.0.0; extra == "langfuse"
Provides-Extra: s3
Requires-Dist: boto3>=1.34.0; extra == "s3"
Provides-Extra: all
Requires-Dist: open-skills[dev,langfuse,s3]; extra == "all"
Dynamic: license-file
